pc_ble_driver_py/config.py
pc_ble_driver_py/observers.py
pc_ble_driver_py/ble_adapter.py
pc_ble_driver_py/exceptions.py
pc_ble_driver_py/__init__.py
pc_ble_driver_py/ble_driver.py
pc_ble_driver_py/ble_driver_types.py
pc_ble_driver_py/hex/__init__.py
pc_ble_driver_py/hex/sd_api_v5/connectivity_4.1.4_usb_for_s132_5.1.0.hex
pc_ble_driver_py/hex/sd_api_v5/connectivity_4.1.4_usb_with_s132_5.1.0_dfu_pkg.zip
pc_ble_driver_py/hex/sd_api_v5/connectivity_4.1.4_usb_with_s132_5.1.0.hex
pc_ble_driver_py/hex/sd_api_v5/__init__.py
pc_ble_driver_py/hex/sd_api_v5/connectivity_4.1.4_1m_with_s132_5.1.0.hex
pc_ble_driver_py/hex/sd_api_v5/s132_nrf52_5.1.0_softdevice.hex
pc_ble_driver_py/hex/sd_api_v2/s132_nrf52_2.0.1_softdevice.hex
pc_ble_driver_py/hex/sd_api_v2/s130_nrf51_2.0.1_softdevice.hex
pc_ble_driver_py/hex/sd_api_v2/connectivity_4.1.4_1m_with_s130_2.0.1.hex
pc_ble_driver_py/hex/sd_api_v2/__init__.py
pc_ble_driver_py/hex/sd_api_v2/connectivity_4.1.4_1m_with_s132_2.0.1.hex
pc_ble_driver_py/examples/heart_rate_collector.py
pc_ble_driver_py/examples/serial_port_enum.py
pc_ble_driver_py/examples/advertising.py
pc_ble_driver_py/examples/__init__.py
pc_ble_driver_py/lib/_nrf_ble_driver_sd_api_v5.so
pc_ble_driver_py/lib/nrf_ble_driver_sd_api_v5.py
pc_ble_driver_py/lib/_nrf_ble_driver_sd_api_v2.so
pc_ble_driver_py/lib/__init__.py
pc_ble_driver_py/lib/nrf_ble_driver_sd_api_v2.py
pc_ble_driver_py.libs/liblzma-07b5b5c8.so.5.2.2
pc_ble_driver_py.libs/libdw-0-780627ce.176.so
pc_ble_driver_py.libs/libbz2-a273e504.so.1.0.6
pc_ble_driver_py.libs/libelf-0-3d9de92a.176.so
pc_ble_driver_py.libs/libudev-9a7475a2.so.1.6.2
pc_ble_driver_py.libs/libcap-79733b59.so.2.22
pc_ble_driver_py.libs/libattr-4f2a9577.so.1.1.0
pc_ble_driver_py-0.17.0.dist-info/WHEEL
pc_ble_driver_py-0.17.0.dist-info/LICENSE
pc_ble_driver_py-0.17.0.dist-info/RECORD
pc_ble_driver_py-0.17.0.dist-info/top_level.txt
pc_ble_driver_py-0.17.0.dist-info/METADATA
