Metadata-Version: 2.1
Name: pc-ble-driver-py
Version: 0.17.0
Summary: Python bindings for the Nordic pc-ble-driver SoftDevice serialization library
Home-page: https://github.com/NordicSemiconductor/pc-ble-driver-py
Author: Nordic Semiconductor ASA
License: Modified BSD License
Keywords: nordic nrf51 nrf52 ble bluetooth softdevice serialization bindings pc-ble-driver pc-ble-driver-py pc_ble_driver pc_ble_driver_py
Platform: UNKNOWN
Classifier: Development Status :: 4 - Beta
Classifier: Intended Audience :: Developers
Classifier: Operating System :: MacOS
Classifier: Operating System :: Microsoft :: Windows
Classifier: Operating System :: POSIX :: Linux
Classifier: Topic :: System :: Networking
Classifier: Topic :: System :: Hardware :: Hardware Drivers
Classifier: Topic :: Software Development :: Embedded Systems
Classifier: License :: Other/Proprietary License
Classifier: Programming Language :: Python
Classifier: Programming Language :: Python :: 3
Classifier: Programming Language :: Python :: 3.7
Classifier: Programming Language :: Python :: 3.8
Classifier: Programming Language :: Python :: 3.9
Classifier: Programming Language :: Python :: 3.10
Requires-Python: >=3.7, <3.11
Requires-Dist: wrapt
Requires-Dist: cryptography
